LICENSE.txt
README.md
setup.py
bigquery/__init__.py
bigquery/ems_api_error.py
bigquery/ems_bigquery_client.py
bigquery/job/__init__.py
bigquery/job/ems_extract_job.py
bigquery/job/ems_job.py
bigquery/job/ems_job_state.py
bigquery/job/ems_load_job.py
bigquery/job/ems_query_job.py
bigquery/job/config/__init__.py
bigquery/job/config/ems_extract_job_config.py
bigquery/job/config/ems_job_config.py
bigquery/job/config/ems_load_job_config.py
bigquery/job/config/ems_query_job_config.py
cloudsql/__init__.py
cloudsql/ems_cloudsql_client.py
cloudsql/ems_cloudsql_util.py
ems_gcp_toolkit.egg-info/PKG-INFO
ems_gcp_toolkit.egg-info/SOURCES.txt
ems_gcp_toolkit.egg-info/dependency_links.txt
ems_gcp_toolkit.egg-info/requires.txt
ems_gcp_toolkit.egg-info/top_level.txt
pubsub/__init__.py
pubsub/ems_message.py
pubsub/ems_publisher_client.py
pubsub/ems_streaming_future.py
pubsub/ems_subscriber_client.py
spanner/__init__.py
spanner/ems_spanner_client.py
storage/__init__.py
storage/ems_storage_client.py
tests/__init__.py
tests/integration/__init__.py
tests/integration/bigquery/__init__.py
tests/integration/bigquery/it_ems_bigquery_client.py
tests/integration/cloudsql/__init__.py
tests/integration/cloudsql/it_ems_cloudsql_client.py
tests/integration/cloudsql/it_ems_cloudsql_util.py
tests/integration/pubsub/__init__.py
tests/integration/pubsub/it_ems_publisher_client.py
tests/integration/pubsub/it_ems_subscriber_client.py
tests/integration/storage/__init__.py
tests/integration/storage/it_ems_storage_client.py
tests/unit/__init__.py
tests/unit/bigquery/__init__.py
tests/unit/bigquery/test_ems_bigquery_client.py
tests/unit/bigquery/job/__init__.py
tests/unit/bigquery/job/test_ems_extract_job.py
tests/unit/bigquery/job/test_ems_load_job.py
tests/unit/bigquery/job/test_ems_query_job.py
tests/unit/bigquery/job/config/__init__.py
tests/unit/bigquery/job/config/test_ems_load_job_config.py
tests/unit/bigquery/job/config/test_ems_query_job_config.py
tests/unit/cloudsql/__init__.py
tests/unit/cloudsql/test_ems_cloudsql_client.py
tests/unit/pubsub/__init__.py
tests/unit/pubsub/test_ems_message.py
tests/unit/storage/__init__.py
tests/unit/storage/test_ems_storage_client.py