Metadata-Version: 2.1
Name: ems-gcp-toolkit
Version: 0.2.2
Home-page: https://github.com/emartech/ems-gcp-toolkit
Author: Emarsys
Author-email: 
License: MIT
License-File: LICENSE.txt
Requires-Dist: google-cloud-storage<3,>=2
Requires-Dist: google-cloud-spanner<4,>=3
Requires-Dist: google-cloud-pubsub<3,>=2
Requires-Dist: google-cloud-bigquery<4,>=3
Requires-Dist: google-cloud-core<3,>=2
Requires-Dist: googleapis-common-protos<2,>=1.63.0
Requires-Dist: grpc-google-iam-v1==0.13.0
